Workbook

Sheet 01_Resumo
A1: Simulador de Viabilidade Técnica e Econômica de Energia Solar
A2: Dados fictícios para demonstração. Premissas ilustrativas e editáveis.
A4: Indicador | B4: Valor | C4: Unidade | E4: Resumo
A5: Potência instalada | B5: =04_Geração!J5 | C5: kWp | E5: Critério: Atrativo quando VPL > 0 e TIR > TMA.
A6: Módulos | B6: =04_Geração!J6 | C6: un | E6: Tarifa, irradiação, CAPEX e CO2 são premissas configuráveis.
A7: Geração anual | B7: =SUM(04_Geração!E5:E16) | C7: kWh
A8: Economia Ano 1 | B8: =06_Fluxo_Caixa!G6 | C8: R$
A9: CAPEX | B9: =05_Custos!B5 | C9: R$
A10: Payback simples | B10: =MATCH(TRUE,06_Fluxo_Caixa!I5:I30>=0,0)-2+(ABS(INDEX(06_Fluxo_Caixa!I5:I30,MATCH(TRUE,06_Fluxo_Caixa!I5:I30>=0,0)-1))/(INDEX(06_Fluxo_Caixa!I5:I30,MATCH(TRUE,06_Fluxo_Caixa!I5:I30>=0,0))-INDEX(06_Fluxo_Caixa!I5:I30,MATCH(TRUE,06_Fluxo_Caixa!I5:I30>=0,0)-1))) | C10: anos
A11: Payback descontado | B11: =MATCH(TRUE,06_Fluxo_Caixa!L5:L30>=0,0)-2+(ABS(INDEX(06_Fluxo_Caixa!L5:L30,MATCH(TRUE,06_Fluxo_Caixa!L5:L30>=0,0)-1))/(INDEX(06_Fluxo_Caixa!L5:L30,MATCH(TRUE,06_Fluxo_Caixa!L5:L30>=0,0))-INDEX(06_Fluxo_Caixa!L5:L30,MATCH(TRUE,06_Fluxo_Caixa!L5:L30>=0,0)-1))) | C11: anos
A12: VPL | B12: =SUM(06_Fluxo_Caixa!K5:K30) | C12: R$
A13: TIR | B13: =IRR(06_Fluxo_Caixa!H5:H30) | C13: %
A14: ROI acumulado em 25 anos | B14: =SUM(06_Fluxo_Caixa!G6:G30)/ABS(06_Fluxo_Caixa!H5) | C14: %
A15: LCOE | B15: =((05_Custos!B5)+SUMPRODUCT(06_Fluxo_Caixa!E6:E30+06_Fluxo_Caixa!F6:F30,06_Fluxo_Caixa!J6:J30))/SUMPRODUCT(06_Fluxo_Caixa!B6:B30,06_Fluxo_Caixa!J6:J30) | C15: R$/kWh
A16: CO2 evitado vida útil | B16: =SUM(06_Fluxo_Caixa!B6:B30)*02_Entradas!B21/1000 | C16: tCO2e
A17: Resultado | B17: =IF(AND(B12>0,B13>02_Entradas!B20),"Atrativo",IF(OR(B12>0,B13>02_Entradas!B20),"Moderado","Pouco atrativo"))

Sheet 02_Entradas
A1: Entradas editáveis
A2: Dados fictícios para demonstração. Premissas ilustrativas e editáveis.
A4: Campo | B4: Valor | C4: Unidade/nota
A5: Perfil | B5: Comercial fictício | C5: Premissa editavel
A6: Estado | B6: SP | C6: Premissa editavel
A7: Cidade | B7: Campinas | C7: Premissa editavel
A8: Consumo médio mensal kWh | B8: 4500 | C8: Premissa editavel
A9: Tarifa compensável R$/kWh | B9: 0.95 | C9: Premissa editavel
A10: Potência módulo Wp | B10: 600 | C10: Premissa editavel
A11: Área módulo m2 | B11: 2.6 | C11: Premissa editavel
A12: Performance Ratio | B12: 0.8 | C12: Premissa editavel
A13: Inversor kW | B13: 45 | C13: Premissa editavel
A14: Disponibilidade | B14: 0.995 | C14: Premissa editavel
A15: Degradação anual | B15: 0.006 | C15: Premissa editavel
A16: Vida útil anos | B16: 25 | C16: Premissa editavel
A17: CAPEX R$/kWp | B17: 4200 | C17: Premissa editavel
A18: OPEX % CAPEX | B18: 0.012 | C18: Premissa editavel
A19: Reajuste tarifário anual | B19: 0.04 | C19: Premissa editavel
... A21: Fator CO2 kg/kWh | B21: 0.0385 | C21: Premissa editavel
A22: Substituição inversor ativa | B22: Sim | C22: Premissa editavel
A23: Ano substituição | B23: 12 | C23: Premissa editavel
A24: Custo substituição R$ | B24: 25000 | C24: Premissa editavel

Sheet 03_Consumo
A1: Consumo
A2: Dados fictícios para demonstração. Premissas ilustrativas e editáveis.
A4: Mes | B4: Consumo kWh
A5: Janeiro | B5: =02_Entradas!$B$8
A6: Fevereiro | B6: =02_Entradas!$B$8
A7: Março | B7: =02_Entradas!$B$8
A8: Abril | B8: =02_Entradas!$B$8
A9: Maio | B9: =02_Entradas!$B$8
A10: Junho | B10: =02_Entradas!$B$8
A11: Julho | B11: =02_Entradas!$B$8
A12: Agosto | B12: =02_Entradas!$B$8
A13: Setembro | B13: =02_Entradas!$B$8
A14: Outubro | B14: =02_Entradas!$B$8
A15: Novembro | B15: =02_Entradas!$B$8
A16: Dezembro | B16: =02_Entradas!$B$8

Sheet 04_Geração
A1: Geração
A2: Dados fictícios para demonstração. Premissas ilustrativas e editáveis.
A4: Mês | B4: Dias | C4: Consumo kWh | D4: HSP | E4: Geração kWh | F4: Déficit/Excedente kWh | G4: Atendimento | I4: Indicador | J4: Valor
A5: Janeiro | B5: 31 | C5: =03_Consumo!B5 | D5: 4.8 | E5: =$J$5*D5*B5*02_Entradas!$B$12*02_Entradas!$B$13 | F5: =E5-C5 | G5: =MIN(E5/C5,1) | I5: Potência instalada kWp | J5: =CEILING(((02_Entradas!$B$8*12/365)/(AVERAGE(D5:D16)*02_Entradas!$B$12))/(02_Entradas!$B$10/1000),1)*(02_Entradas!$B$10/1000)
A6: Fevereiro | B6: 28 | C6: =03_Consumo!B6 | D6: 5 | E6: =$J$5*D6*B6*02_Entradas!$B$12*02_Entradas!$B$13 | F6: =E6-C6 | G6: =MIN(E6/C6,1) | I6: Módulos | J6: =J5/(02_Entradas!$B$10/1000)
A7: Março | B7: 31 | C7: =03_Consumo!B7 | D7: 5.1 | E7: =$J$5*D7*B7*02_Entradas!$B$12*02_Entradas!$B$13 | F7: =E7-C7 | G7: =MIN(E7/C7,1) | I7: Área m2 | J7: =J6*02_Entradas!$B$11
A8: Abril | B8: 30 | C8: =03_Consumo!B8 | D8: 5 | E8: =$J$5*D8*B8*02_Entradas!$B$12*02_Entradas!$B$13 | F8: =E8-C8 | G8: =MIN(E8/C8,1) | I8: DC/AC | J8: =J5/02_Entradas!$B$13
A9: Maio | B9: 31 | C9: =03_Consumo!B9 | D9: 4.6 | E9: =$J$5*D9*B9*02_Entradas!$B$12*02_Entradas!$B$13 | F9: =E9-C9 | G9: =MIN(E9/C9,1)
A10: Junho | B10: 30 | C10: =03_Consumo!B10 | D10: 4.3 | E10: =$J$5*D10*B10*02_Entradas!$B$12*02_Entradas!$B$13 | F10: =E10-C10 | G10: =MIN(E10/C10,1)
A11: Julho | B11: 31 | C11: =03_Consumo!B11 | D11: 4.5 | E11: =$J$5*D11*B11*02_Entradas!$B$12*02_Entradas!$B$13 | F11: =E11-C11 | G11: =MIN(E11/C11,1)
A12: Agosto | B12: 31 | C12: =03_Consumo!B12 | D12: 4.9 | E12: =$J$5*D12*B12*02_Entradas!$B$12*02_Entradas!$B$13 | F12: =E12-C12 | G12: =MIN(E12/C12,1)
A13: Setembro | B13: 30 | C13: =03_Consumo!B13 | D13: 5 | E13: =$J$5*D13*B13*02_Entradas!$B$12*02_Entradas!$B$13 | F13: =E13-C13 | G13: =MIN(E13/C13,1)
A14: Outubro | B14: 31 | C14: =03_Consumo!B14 | D14: 5.2 | E14: =$J$5*D14*B14*02_Entradas!$B$12*02_Entradas!$B$13 | F14: =E14-C14 | G14: =MIN(E14/C14,1)
A15: Novembro | B15: 30 | C15: =03_Consumo!B15 | D15: 5.1 | E15: =$J$5*D15*B15*02_Entradas!$B$12*02_Entradas!$B$13 | F15: =E15-C15 | G15: =MIN(E15/C15,1)
A16: Dezembro | B16: 31 | C16: =03_Consumo!B16 | D16: 4.9 | E16: =$J$5*D16*B16*02_Entradas!$B$12*02_Entradas!$B$13 | F16: =E16-C16 | G16: =MIN(E16/C16,1)

Sheet 05_Custos
A1: Custos
A2: Dados fictícios para demonstração. Premissas ilustrativas e editáveis.
A4: Item | B4: Valor | C4: Nota
A5: CAPEX total | B5: =04_Geração!J5*02_Entradas!$B$17 | C5: Instalado kWp x R$/kWp
A6: CAPEX R$/kWp | B6: =02_Entradas!$B$17 | C6: Premissa
A7: OPEX anual | B7: =B5*02_Entradas!$B$18 | C7: Percentual do CAPEX
A8: Substituição inversor | B8: =IF(02_Entradas!$B$22="Sim",02_Entradas!$B$24,0) | C8: Evento opcional

Sheet 06_Fluxo_Caixa
A1: Fluxo de Caixa
A2: Dados fictícios para demonstração. Premissas ilustrativas e editáveis.
A4: Ano | B4: Geração kWh | C4: Tarifa R$/kWh | D4: Economia bruta | E4: OPEX | F4: Custos extraordinários | G4: Economia líquida | H4: Fluxo de caixa | I4: Fluxo acumulado | J4: Fator desconto | K4: Fluxo descontado | L4: Fluxo descontado acumulado
A5: 0 | B5: 0 | C5: =02_Entradas!$B$9 | D5: 0 | E5: 0 | F5: 0 | G5: 0 | H5: =-05_Custos!$B$5 | I5: =-05_Custos!$B$5 | J5: 1 | K5: =-05_Custos!$B$5 | L5: =-05_Custos!$B$5
A6: 1 | B6: =SUM(04_Geração!$E$5:$E$16)*(1-02_Entradas!$B$14)^(A6-1) | C6: =02_Entradas!$B$9*(1+02_Entradas!$B$19)^(A6-1) | D6: =B6*C6 | E6: =05_Custos!$B$7 | F6: =IF(A6=02_Entradas!$B$23,05_Custos!$B$8,0) | G6: =D6-E6-F6 | H6: =G6 | I6: =H6+I5 | J6: =1/(1+02_Entradas!$B$20)^A6 | K6: =H6*J6 | L6: =K6+L5
A7: 2 | B7: =SUM(04_Geração!$E$5:$E$16)*(1-02_Entradas!$B$14)^(A7-1) | C7: =02_Entradas!$B$9*(1+02_Entradas!$B$19)^(A7-1) | D7: =B7*C7 | E7: =05_Custos!$B$7 | F7: =IF(A7=02_Entradas!$B$23,05_Custos!$B$8,0) | G7: =D7-E7-F7 | H7: =G7 | I7: =H7+I6 | J7: =1/(1+02_Entradas!$B$20)^A7 | K7: =H7*J7 | L7: =K7+L6
A8: 3 | B8: =SUM(04_Geração!$E$5:$E$16)*(1-02_Entradas!$B$14)^(A8-1) | C8: =02_Entradas!$B$9*(1+02_Entradas!$B$19)^(A8-1) | D8: =B8*C8 | E8: =05_Custos!$B$7 | F8: =IF(A8=02_Entradas!$B$23,05_Custos!$B$8,0) | G8: =D8-E8-F8 | H8: =G8 | I8: =H8+I7 | J8: =1/(1+02_Entradas!$B$20)^A8 | K8: =H8*J8 | L8: =K8+L7
A9: 4 | B9: =SUM(04_Geração!$E$5:$E$16)*(1-02_Entradas!$B$14)^(A9-1) | C9: =02_Entradas!$B$9*(1+02_Entradas!$B$19)^(A9-1) | D9: =B9*C9 | E9: =05_Custos!$B$7 | F9: =IF(A9=02_Entradas!$B$23,05_Custos!$B$8,0) | G9: =D9-E9-F9 | H9: =G9 | I9: =H9+I8 | J9: =1/(1+02_Entradas!$B$20)^A9 | K9: =H9*J9 | L9: =K9+L8
A10: 5 | B10: =SUM(04_Geração!$E$5:$E$16)*(1-02_Entradas!$B$14)^(A10-1) | C10: =02_Entradas!$B$9*(1+02_Entradas!$B$19)^(A10-1) | D10: =B10*C10 | E10: =05_Custos!$B$7 | F10: =IF(A10=02_Entradas!$B$23,05_Custos!$B$8,0) | G10: =D10-E10-F10 | H10: =G10 | I10: =H10+I9 | J10: =1/(1+02_Entradas!$B$20)^A10 | K10: =H10*J10 | L10: =K10+L9
A11: 6 | B11: =SUM(04_Geração!$E$5:$E$16)*(1-02_Entradas!$B$14)^(A11-1) | C11: =02_Entradas!$B$9*(1+02_Entradas!$B$19)^(A11-1) | D11: =B11*C11 | E11: =05_Custos!$B$7 | F11: =IF(A11=02_Entradas!$B$23,05_Custos!$B$8,0) | G11: =D11-E11-F11 | H11: =G11 | I11: =H11+I10 | J11: =1/(1+02_Entradas!$B$20)^A11 | K11: =H11*J11 | L11: =K11+L10
A12: 7 | B12: =SUM(04_Geração!$E$5:$E$16)*(1-02_Entradas!$B$14)^(A12-1) | C12: =02_Entradas!$B$9*(1+02_Entradas!$B$19)^(A12-1) | D12: =B12*C12 | E12: =05_Custos!$B$7 | F12: =IF(A12=02_Entradas!$B$23,05_Custos!$B$8,0) | G12: =D12-E12-F12 | H12: =G12 | I12: =H12+I11 | J12: =1/(1+02_Entradas!$B$20)^A12 | K12: =H12*J12 | L12: =K12+L11
A13: 8 | B13: =SUM(04_Geração!$E$5:$E$16)*(1-02_Entradas!$B$14)^(A13-1) | C13: =02_Entradas!$B$9*(1+02_Entradas!$B$19)^(A13-1) | D13: =B13*C13 | E13: =05_Custos!$B$7 | F13: =IF(A13=02_Entradas!$B$23,05_Custos!$B$8,0) | G13: =D13-E13-F13 | H13: =G13 | I13: =H13+I12 | J13: =1/(1+02_Entradas!$B$20)^A13 | K13: =H13*J13 | L13: =K13+L12
A14: 9 | B14: =SUM(04_Geração!$E$5:$E$16)*(1-02_Entradas!$B$14)^(A14-1) | C14: =02_Entradas!$B$9*(1+02_Entradas!$B$19)^(A14-1) | D14: =B14*C14 | E14: =05_Custos!$B$7 | F14: =IF(A14=02_Entradas!$B$23,05_Custos!$B$8,0) | G14: =D14-E14-F14 | H14: =G14 | I14: =H14+I13 | J14: =1/(1+02_Entradas!$B$20)^A14 | K14: =H14*J14 | L14: =K14+L13
A15: 10 | B15: =SUM(04_Geração!$E$5:$E$16)*(1-02_Entradas!$B$14)^(A15-1) | C15: =02_Entradas!$B$9*(1+02_Entradas!$B$19)^(A15-1) | D15: =B15*C15 | E15: =05_Custos!$B$7 | F15: =IF(A15=02_Entradas!$B$23,05_Custos!$B$8,0) | G15: =D15-E15-F15 | H15: =G15 | I15: =H15+I14 | J15: =1/(1+02_Entradas!$B$20)^A15 | K15: =H15*J15 | L15: =K15+L14
A16: 11 | B16: =SUM(04_Geração!$E$5:$E$16)*(1-02_Entradas!$B$14)^(A16-1) | C16: =02_Entradas!$B$9*(1+02_Entradas!$B$19)^(A16-1) | D16: =B16*C16 | E16: =05_Custos!$B$7 | F16: =IF(A16=02_Entradas!$B$23,05_Custos!$B$8,0) | G16: =D16-E16-F16 | H16: =G16 | I16: =H16+I15 | J16: =1/(1+02_Entradas!$B$20)^A16 | K16: =H16*J16 | L16: =K16+L15
A17: 12 | B17: =SUM(04_Geração!$E$5:$E$16)*(1-02_Entradas!$B$14)^(A17-1) | C17: =02_Entradas!$B$9*(1+02_Entradas!$B$19)^(A17-1) | D17: =B17*C17 | E17: =05_Custos!$B$7 | F17: =IF(A17=02_Entradas!$B$23,05_Custos!$B$8,0) | G17: =D17-E17-F17 | H17: =G17 | I17: =H17+I16 | J17: =1/(1+02_Entradas!$B$20)^A17 | K17: =H17*J17 | L17: =K17+L16
... A30: 25 | B30: =SUM(04_Geração!$E$5:$E$16)*(1-02_Entradas!$B$14)^(A30-1) | C30: =02_Entradas!$B$9*(1+02_Entradas!$B$19)^(A30-1) | D30: =B30*C30 | E30: =05_Custos!$B$7 | F30: =IF(A30=02_Entradas!$B$23,05_Custos!$B$8,0) | G30: =D30-E30-F30 | H30: =G30 | I30: =H30+I29 | J30: =1/(1+02_Entradas!$B$20)^A30 | K30: =H30*J30 | L30: =K30+L29

Sheet 07_Cenários
A1: Cenários
A2: Dados fictícios para demonstração. Premissas ilustrativas e editáveis.
A4: Cenário | B4: Potência kWp | C4: Geração anual | D4: CAPEX | E4: Economia Ano 1 | F4: Payback | G4: VPL | H4: TIR | I4: LCOE | J4: Economia total
A5: Conservador | B5: 40.2 | C5: 53989.05 | D5: 185724 | E5: 49060.91 | F5: 3.7104871 | G5: 233568.39 | H5: 0.27589274 | I5: 0.51529164 | J5: 1439660.3
A6: Base | B6: 38.4 | C6: 54285.926 | D6: 161280 | E6: 49636.27 | F6: 3.1288068 | G6: 426940.58 | H6: 0.34083092 | I6: 0.3962387 | J6: 1902515.4
A7: Otimista | B7: 36.6 | C7: 54328.337 | D7: 141422.4 | E7: 49914.852 | F7: 2.7214629 | G7: 571132.03 | H7: 0.39658934 | I7: 0.32776036 | J7: 2192332.3

Sheet 08_Sensibilidade
A1: Sensibilidade
A2: Dados fictícios para demonstração. Premissas ilustrativas e editáveis.
A4: Variável | B4: Variação | C4: Payback | D4: Payback descontado | E4: VPL | F4: TIR | G4: LCOE | H4: ROI acumulado
A5: capex | B5: -0.2 | C5: 2.5084784 | D5: 3.0138455 | E5: 462710.05 | F5: 0.42118357 | G5: 0.32037011 | H5: 14.820438
A6: capex | B6: -0.1 | C6: 2.8197631 | D6: 3.4541819 | E6: 444825.32 | F6: 0.37658223 | G6: 0.3583044 | H6: 13.140389
A7: capex | B7: 0 | C7: 3.1288068 | D7: 3.897615 | E7: 426940.58 | F7: 0.34083092 | G7: 0.3962387 | H7: 11.796351
A8: capex | B8: 0.1 | C8: 3.433917 | D8: 4.3657679 | E8: 409055.85 | F8: 0.31149823 | G8: 0.43417299 | H8: 10.696682
A9: capex | B9: 0.2 | C9: 3.7411883 | D9: 4.8436034 | E9: 391171.11 | F9: 0.2869629 | G9: 0.47210729 | H9: 9.7802921
A10: tariff | B10: -0.2 | C10: 3.8956415 | D10: 5.0889912 | E10: 304189.84 | F10: 0.27571408 | G10: 0.3962387 | H10: 9.3460784
A11: tariff | B11: -0.1 | C11: 3.4679512 | D11: 4.4186998 | E11: 365565.21 | F11: 0.30838674 | G11: 0.3962387 | H11: 10.571214
A12: tariff | B12: 0 | C12: 3.1288068 | D12: 3.897615 | E12: 426940.58 | F12: 0.34083092 | G12: 0.3962387 | H12: 11.796351
A13: tariff | B13: 0.1 | C13: 2.8481737 | D13: 3.4943655 | E13: 488315.95 | F13: 0.37312884 | G13: 0.3962387 | H13: 13.021487
A14: tariff | B14: 0.2 | C14: 2.6119897 | D14: 3.1602822 | E14: 549691.32 | F14: 0.4053307 | G14: 0.3962387 | H14: 14.246623
A15: generation | B15: -0.2 | C15: 3.8956415 | D15: 5.0889912 | E15: 382228.75 | F15: 0.27612974 | G15: 0.49107444 | H15: 9.3770804
A16: generation | B16: -0.1 | C16: 3.4679512 | D16: 4.4186998 | E16: 406420.16 | F16: 0.30855676 | G16: 0.43841436 | H16: 10.586497
... A34: degradation | B34: 0.2 | C34: 3.1356271 | D34: 3.9100766 | E34: 416101.3 | F34: 0.33866265 | G34: 0.40201217 | H34: 11.463967

Sheet 09_Mapa_CAPEX_Tarifa
A1: Mapa de calor: CAPEX x tarifa
A2: Dados fictícios para demonstração. Premissas ilustrativas e editáveis.
A4: Variação CAPEX | B4: Variação tarifa | C4: Payback simples | D4: VPL | E4: TIR | F4: ROI acumulado | G4: Classificação
A5: -0.2 | B5: -0.2 | C5: 3.1288068 | D5: 339959.31 | E5: 0.340473 | F5: 11.757598 | G5: Atrativo
A6: -0.2 | B6: -0.1 | C6: 2.7850644 | D6: 401334.68 | E6: 0.38090469 | F6: 13.289018 | G6: Atrativo
A7: -0.2 | B7: 0 | C7: 2.5084784 | D7: 462710.05 | E7: 0.42118357 | F7: 14.820438 | G7: Atrativo
A8: -0.2 | B8: 0.1 | C8: 2.2834987 | D8: 524085.42 | E8: 0.46136516 | F8: 16.351858 | G8: Atrativo
A9: -0.2 | B9: 0.2 | C9: 2.0969145 | D9: 585460.79 | E9: 0.50148237 | F9: 17.883278 | G9: Atrativo
A10: -0.1 | B10: -0.2 | C10: 3.5105314 | D10: 322074.58 | E10: 0.30457358 | F10: 10.417865 | G10: Atrativo
A11: -0.1 | B11: -0.1 | C11: 3.1288068 | D11: 383449.95 | E11: 0.34067203 | F11: 11.779127 | G11: Atrativo
A12: -0.1 | B12: 0 | C12: 2.8197631 | D12: 444825.32 | E12: 0.37658223 | F12: 13.140389 | G12: Atrativo
A13: -0.1 | B13: 0.1 | C13: 2.5649082 | D13: 506200.68 | E13: 0.41237293 | F13: 14.501652 | G13: Atrativo
A14: -0.1 | B14: 0.2 | C14: 2.3536781 | D14: 567576.05 | E14: 0.4480852 | F14: 15.862914 | G14: Atrativo
A15: 0 | B15: -0.2 | C15: 3.8956415 | D15: 304189.84 | E15: 0.27571408 | F15: 9.3460784 | G15: Atrativo
A16: 0 | B16: -0.1 | C16: 3.4679512 | D16: 365565.21 | E16: 0.30838674 | F16: 10.571214 | G16: Atrativo
... A29: 0.2 | B29: 0.2 | C29: 3.1288068 | D29: 513921.85 | E29: 0.34106871 | F29: 11.822186 | G29: Atrativo

Sheet 10_Premissas
A1: Premissas
A2: Dados fictícios para demonstração. Premissas ilustrativas e editáveis.
A4: Premissa | B4: Valor padrao | C4: Unidade | D4: Fonte | E4: Editavel | F4: Descricao
A5: Consumo | B5: 4500 | C5: kWh/mês | D5: Sintético | E5: Sim | F5: Cliente comercial fictício.
A6: Tarifa | B6: 0.95 | C6: R$/kWh | D6: Premissa sintética | E6: Sim | F6: Tarifa compensável configurável. Não é tarifa oficial.
A7: HSP | B7: 4.87 | C7: h/dia | D7: Premissa ilustrativa | E7: Sim | F7: Média do exemplo.
A8: Performance Ratio | B8: 0.8 | C8: % | D8: Premissa técnica | E8: Sim | F8: Eficiência global.
A9: CAPEX | B9: 4200 | C9: R$/kWp | D9: Premissa ilustrativa | E9: Sim | F9: Investimento por kWp.
A10: OPEX | B10: 0.012 | C10: % CAPEX | D10: Premissa ilustrativa | E10: Sim | F10: Custos anuais.
A11: CO2 | B11: 0.0385 | C11: kg/kWh | D11: Premissa ilustrativa | E11: Sim | F11: Substituir por fonte oficial se usado publicamente.

Sheet 11_Documentação
A1: Documentação
A2: Dados fictícios para demonstração. Premissas ilustrativas e editáveis.
A4: Topico | B4: Descricao
A5: Objetivo | B5: Avaliar viabilidade técnica e financeira de sistema fotovoltaico.
A6: Limitação | B6: Modelo simplificado. Não substitui projeto executivo, estudo de conexão ou análise tarifária específica.
A7: Fórmula FV | B7: Potência kWp = consumo diário / (HSP x PR).
A8: Payback | B8: Calculado por fluxo acumulado, com interpolação anual.
A9: VPL | B9: Soma dos fluxos descontados pela TMA.
A10: TIR | B10: Taxa que zera o VPL do fluxo de caixa.
A11: ROI | B11: ROI acumulado em 25 anos = economia líquida acumulada / CAPEX.
A12: LCOE | B12: Valor presente de CAPEX, OPEX e custos extraordinários dividido pela energia degradada descontada.
